pandarus/__init__.py
pandarus/calculate.py
pandarus/conversion.py
pandarus/filesystem.py
pandarus/geometry.py
pandarus/intersections.py
pandarus/maps.py
pandarus/projection.py
pandarus/rasters.py
pandarus-1.0.4.dist-info/DESCRIPTION.rst
pandarus-1.0.4.dist-info/METADATA
pandarus-1.0.4.dist-info/RECORD
pandarus-1.0.4.dist-info/WHEEL
pandarus-1.0.4.dist-info/metadata.json
pandarus-1.0.4.dist-info/top_level.txt
