Metadata-Version: 2.0
Name: pandarus
Version: 1.0.4
Summary: UNKNOWN
Home-page: https://github.com/cmutel/pandarus
Author: Chris Mutel
Author-email: cmutel@gmail.com
License: Copyright (c) 2016, Chris Mutel and ETH Zürich.
Requires-Dist: Rtree
Requires-Dist: appdirs
Requires-Dist: fiona
Requires-Dist: numpy
Requires-Dist: pyproj
Requires-Dist: rasterio
Requires-Dist: rasterstats
Requires-Dist: shapely
